cythoncubicspline/LICENSE.txt
cythoncubicspline/README.MD
cythoncubicspline/__init__.py
cythoncubicspline/cycythoncubicspline.pyx
cythoncubicspline/cycythoncubicspline_compile.py
cythoncubicspline/requirements.txt
cythoncubicspline/thirdparty.json
cythoncubicspline-0.11.dist-info/LICENSE.rst
cythoncubicspline-0.11.dist-info/METADATA
cythoncubicspline-0.11.dist-info/WHEEL
cythoncubicspline-0.11.dist-info/top_level.txt
cythoncubicspline-0.11.dist-info/RECORD
