Metadata-Version: 2.1
Name: cythoncubicspline
Version: 0.11
Summary: Some useful algorithms in pure Cython - no dependencies
Home-page: https://github.com/hansalemaos/cythoncubicspline
Author: Johannes Fischer
Author-email: aulasparticularesdealemaosp@gmail.com
License: MIT
Keywords: cython
Classifier: Development Status :: 4 - Beta
Classifier: Programming Language :: Python :: 3 :: Only
Classifier: Programming Language :: Python :: 3.10
Classifier: Topic :: Software Development :: Libraries :: Python Modules
Classifier: Topic :: Utilities
License-File: LICENSE.rst
Requires-Dist: Cython
Requires-Dist: setuptools
